npblind/__init__.py
npblind/core/__init__.py
npblind/core/tools.py
npblind-0.0.10.dist-info/LICENSE
npblind-0.0.10.dist-info/METADATA
npblind-0.0.10.dist-info/WHEEL
npblind-0.0.10.dist-info/top_level.txt
npblind-0.0.10.dist-info/RECORD
