Metadata-Version: 2.1
Name: npblind
Version: 0.0.10
Summary: A package to help managing data privacy
Home-page: https://github.com/noppGithub/npgcs
Author: Nopporn Phantawee
Author-email: n.phantawee@gmail.com
License: MIT
Classifier: Development Status :: 3 - Alpha
Classifier: Intended Audience :: Developers
Classifier: License :: OSI Approved :: MIT License
Classifier: Operating System :: OS Independent
Classifier: Programming Language :: Python :: 3
Classifier: Programming Language :: Python :: 3.6
Classifier: Programming Language :: Python :: 3.7
Classifier: Programming Language :: Python :: 3.8
Classifier: Programming Language :: Python :: 3.9
Classifier: Programming Language :: Python :: 3.10
Classifier: Programming Language :: Python :: 3 :: Only
Requires-Python: >=3.6, <4
License-File: LICENSE
Requires-Dist: google-cloud-datacatalog
Requires-Dist: google-cloud-dlp
Requires-Dist: npgbq >=2.1.3
Provides-Extra: dev
Requires-Dist: pandas ; extra == 'dev'
Provides-Extra: test
Requires-Dist: pandas ; extra == 'test'
